{
  "products": [
    {
      "name": "bánh kem baby three",
      "description": "",
      "category": "Bánh kem sinh nhật",
      "price_range": "~250,000 - 380,000đ (tham khảo, liên hệ báo giá chính xác)"
    },
    {
      "name": "mousse dừa size 18x36",
      "description": "",
      "category": "Mousse/Cheese Cake",
      "price_range": "~200,000 - 350,000đ (tham khảo, liên hệ báo giá chính xác)"
    },
    {
      "name": "cupcake",
      "description": "",
      "category": "Cupcake",
      "price_range": "~25,000 - 45,000đ/cái (tham khảo, liên hệ báo giá chính xác)"
    },
    {
      "name": "bánh kem cưới",
      "description": "",
      "category": "Bánh cưới",
      "price_range": "~1,500,000 - 5,000,000đ (tham khảo, liên hệ báo giá chính xác)"
    },
    {
      "name": "bánh kem pokemon",
      "description": "",
      "category": "Bánh chủ đề theo yêu cầu",
      "price_range": "~380,000 - 600,000đ (tham khảo, liên hệ báo giá chính xác)"
    },
    {
      "name": "bánh kem 2 tầng - nam",
      "description": "",
      "category": "Bánh tầng",
      "price_range": "~800,000 - 1,500,000đ (tham khảo, liên hệ báo giá chính xác)"
    },
    {
      "name": "bánh kem 2 tầng - bé gái",
      "description": "",
      "category": "Bánh tầng",
      "price_range": "~800,000 - 1,500,000đ (tham khảo, liên hệ báo giá chính xác)"
    },
    {
      "name": "bánh kem 2 tầng - công ty",
      "description": "",
      "category": "Bánh tầng",
      "price_range": "~1,000,000 - 2,000,000đ (tham khảo, liên hệ báo giá chính xác)"
    },
    {
      "name": "bánh kem số",
      "description": "",
      "category": "Bánh chữ & số",
      "price_range": "~350,000 - 600,000đ (tham khảo, liên hệ báo giá chính xác)"
    },
    {
      "name": "bánh kem công ty",
      "description": "",
      "category": "Bánh logo & công ty",
      "price_range": "~400,000 - 800,000đ (tham khảo, liên hệ báo giá chính xác)"
    },
    {
      "name": "bánh kem tim",
      "description": "",
      "category": "Bánh mẫu tim",
      "price_range": "~280,000 - 500,000đ (tham khảo, liên hệ báo giá chính xác)"
    },
    {
      "name": "bánh kem quả mông",
      "description": "",
      "category": "Bánh nặn tạo hình",
      "price_range": "~300,000 - 500,000đ (tham khảo, liên hệ báo giá chính xác)"
    },
    {
      "name": "bánh kem xe cảnh sát",
      "description": "",
      "category": "Bánh máy bay, ô tô, siêu nhân",
      "price_range": "~380,000 - 650,000đ (tham khảo, liên hệ báo giá chính xác)"
    },
    {
      "name": "bánh kemcon vật",
      "description": "",
      "category": "Bánh kem con vật",
      "price_range": "~350,000 - 600,000đ (tham khảo, liên hệ báo giá chính xác)"
    },
    {
      "name": "bánh kem con mèo",
      "description": "",
      "category": "Bánh kem con vật",
      "price_range": "~350,000 - 600,000đ (tham khảo, liên hệ báo giá chính xác)"
    },
    {
      "name": "bánh kem con mèo thần tài",
      "description": "",
      "category": "Bánh kem con vật",
      "price_range": "~380,000 - 650,000đ (tham khảo, liên hệ báo giá chính xác)"
    },
    {
      "name": "bánh kem capybara",
      "description": "",
      "category": "Bánh kem con vật",
      "price_range": "~380,000 - 650,000đ (tham khảo, liên hệ báo giá chính xác)"
    },
    {
      "name": "Bánh tầng",
      "description": "Bánh tầng với nhiều sản phẩm.",
      "category": "Bánh tầng",
      "price_range": "~700,000 - 2,000,000đ (tham khảo, liên hệ báo giá chính xác)"
    },
    {
      "name": "Bánh kẹo, chocolate",
      "description": "Bánh kẹo và chocolate với nhiều sản phẩm.",
      "category": "Bánh kẹo, chocolate",
      "price_range": "~20,000 - 80,000đ/cái (tham khảo, liên hệ báo giá chính xác)"
    },
    {
      "name": "Bánh mới",
      "description": "Các loại bánh mới nhất.",
      "category": "Bánh mới",
      "price_range": "Liên hệ để báo giá chính xác"
    },
    {
      "name": "Bánh mini",
      "description": "Bánh mini cho những dịp đặc biệt.",
      "category": "Bánh mini",
      "price_range": "~80,000 - 180,000đ (tham khảo, liên hệ báo giá chính xác)"
    },
    {
      "name": "Bánh mừng thọ ông bà",
      "description": "Bánh dành cho dịp mừng thọ ông bà.",
      "category": "Bánh mừng thọ ông bà",
      "price_range": "~380,000 - 800,000đ (tham khảo, liên hệ báo giá chính xác)"
    },
    {
      "name": "Bánh ngọt mỗi ngày",
      "description": "Bánh ngọt cho mỗi ngày.",
      "category": "Bánh ngọt mỗi ngày",
      "price_range": "~15,000 - 60,000đ/cái (tham khảo, liên hệ báo giá chính xác)"
    },
    {
      "name": "Bánh hũ vàng & khai trương",
      "description": "Bánh để chúc mừng khai trương.",
      "category": "Bánh hũ vàng & khai trương",
      "price_range": "~500,000 - 1,500,000đ (tham khảo, liên hệ báo giá chính xác)"
    },
    {
      "name": "Bánh nặn tạo hình",
      "description": "Bánh được tạo hình theo yêu cầu.",
      "category": "Bánh nặn tạo hình",
      "price_range": "~400,000 - 900,000đ (tham khảo, liên hệ báo giá chính xác)"
    },
    {
      "name": "Bánh mẫu tim",
      "description": "Bánh hình mẫu tim.",
      "category": "Bánh mẫu tim",
      "price_range": "~280,000 - 500,000đ (tham khảo, liên hệ báo giá chính xác)"
    },
    {
      "name": "Bánh 18+",
      "description": "Bánh cho độ tuổi 18.",
      "category": "Bánh 18+",
      "price_range": "~380,000 - 700,000đ (tham khảo, liên hệ báo giá chính xác)"
    },
    {
      "name": "Bánh chủ đề theo yêu cầu",
      "description": "Bánh theo chủ đề yêu cầu của khách hàng.",
      "category": "Bánh chủ đề theo yêu cầu",
      "price_range": "~400,000 - 900,000đ (tham khảo, liên hệ báo giá chính xác)"
    },
    {
      "name": "Bánh chữ & số",
      "description": "Bánh với chữ và số.",
      "category": "Bánh chữ & số",
      "price_range": "~350,000 - 600,000đ (tham khảo, liên hệ báo giá chính xác)"
    },
    {
      "name": "Bánh cưới",
      "description": "Bánh cưới cho ngày trọng đại.",
      "category": "Bánh cưới",
      "price_range": "~1,500,000 - 5,000,000đ (tham khảo, liên hệ báo giá chính xác)"
    },
    {
      "name": "Bánh hoa",
      "description": "Bánh trang trí hoa.",
      "category": "Bánh hoa",
      "price_range": "~300,000 - 650,000đ (tham khảo, liên hệ báo giá chính xác)"
    },
    {
      "name": "Bánh trái cây",
      "description": "Bánh với trái cây tươi.",
      "category": "Bánh trái cây",
      "price_range": "~320,000 - 650,000đ (tham khảo, liên hệ báo giá chính xác)"
    },
    {
      "name": "Bánh búp bê",
      "description": "Bánh hình búp bê.",
      "category": "Bánh búp bê",
      "price_range": "~400,000 - 750,000đ (tham khảo, liên hệ báo giá chính xác)"
    },
    {
      "name": "Bánh máy bay, ô tô, siêu nhân",
      "description": "Bánh với hình máy bay, ô tô, siêu nhân.",
      "category": "Bánh máy bay, ô tô, siêu nhân",
      "price_range": "~400,000 - 800,000đ (tham khảo, liên hệ báo giá chính xác)"
    },
    {
      "name": "Bánh kem con vật",
      "description": "Bánh kem hình con vật.",
      "category": "Bánh kem con vật",
      "price_range": "~350,000 - 700,000đ (tham khảo, liên hệ báo giá chính xác)"
    },
    {
      "name": "Bánh logo & công ty",
      "description": "Bánh với logo công ty.",
      "category": "Bánh logo & công ty",
      "price_range": "~400,000 - 900,000đ (tham khảo, liên hệ báo giá chính xác)"
    },
    {
      "name": "Bánh vẽ",
      "description": "Bánh có vẽ trang trí.",
      "category": "Bánh vẽ",
      "price_range": "~350,000 - 700,000đ (tham khảo, liên hệ báo giá chính xác)"
    },
    {
      "name": "Bánh bé gái",
      "description": "Bánh dành cho bé gái.",
      "category": "Bánh bé gái",
      "price_range": "~300,000 - 650,000đ (tham khảo, liên hệ báo giá chính xác)"
    },
    {
      "name": "Bánh bé trai",
      "description": "Bánh dành cho bé trai.",
      "category": "Bánh bé trai",
      "price_range": "~300,000 - 650,000đ (tham khảo, liên hệ báo giá chính xác)"
    },
    {
      "name": "Mousse dừa",
      "description": "",
      "category": "Mousse/Cheese Cake",
      "price_range": "~150,000 - 350,000đ (tham khảo, liên hệ báo giá chính xác)"
    },
    {
      "name": "Mix Vị",
      "description": "",
      "category": "Mousse/Cheese Cake",
      "price_range": "~150,000 - 350,000đ (tham khảo, liên hệ báo giá chính xác)"
    },
    {
      "name": "Red velvet",
      "description": "",
      "category": "Mousse/Cheese Cake",
      "price_range": "~200,000 - 420,000đ (tham khảo, liên hệ báo giá chính xác)"
    },
    {
      "name": "Panna cotta",
      "description": "",
      "category": "",
      "price_range": "~40,000 - 80,000đ/hũ (tham khảo, liên hệ báo giá chính xác)"
    },
    {
      "name": "Bánh mì chà bông sốt bơ",
      "description": "Hết hàng",
      "category": "",
      "price_range": "45,000₫"
    },
    {
      "name": "Cupcake trứng muối",
      "description": "Hết hàng",
      "category": "",
      "price_range": "60,000₫"
    },
    {
      "name": "Tart dừa nướng",
      "description": "Hết hàng",
      "category": "",
      "price_range": "15,000₫"
    },
    {
      "name": "Set mochi 4 vị",
      "description": "",
      "category": "",
      "price_range": "120,000₫"
    },
    {
      "name": "Sữa chua nếp cẩm",
      "description": "Hết hàng",
      "category": "",
      "price_range": "12,000₫"
    },
    {
      "name": "Su sầu riêng phomai",
      "description": "Hết hàng",
      "category": "",
      "price_range": "70,000₫"
    },
    {
      "name": "Bánh mì kem chocolate",
      "description": "Hết hàng",
      "category": "",
      "price_range": "50,000₫"
    },
    {
      "name": "Sữa chua trân châu đường đen",
      "description": "Hết hàng",
      "category": "",
      "price_range": "12,000₫"
    },
    {
      "name": "Chocolate Mochi cookies",
      "description": "Hết hàng",
      "category": "",
      "price_range": "20,000₫"
    },
    {
      "name": "Bánh bao chỉ",
      "description": "",
      "category": "",
      "price_range": "20,000₫"
    },
    {
      "name": "Set 3 donut nhân mix vị",
      "description": "",
      "category": "",
      "price_range": "55,000₫"
    },
    {
      "name": "Sừng trâu kimsa",
      "description": "Hết hàng",
      "category": "",
      "price_range": "70,000₫"
    },
    {
      "name": "Bánh mì kimsa",
      "description": "Hết hàng",
      "category": "",
      "price_range": "60,000₫"
    },
    {
      "name": "Sữa chua mít",
      "description": "",
      "category": "",
      "price_range": "12,000₫"
    },
    {
      "name": "Sữa chua cốm",
      "description": "",
      "category": "",
      "price_range": "12,000₫"
    },
    {
      "name": "Bánh sữa chua phomai nướng",
      "description": "",
      "category": "",
      "price_range": "40,000₫"
    },
    {
      "name": "Bánh mousse dừa hộp",
      "description": "",
      "category": "",
      "price_range": "50,000₫"
    },
    {
      "name": "Bánh phomai cháy",
      "description": "",
      "category": "",
      "price_range": "30,000₫"
    },
    {
      "name": "Bánh tiramisu ly",
      "description": "",
      "category": "",
      "price_range": "35,000₫"
    }
  ],
  "contact": {
    "phone": "0935 226 206",
    "zalo": "0935226206",
    "address": "107 Đ. Lê Đình Dương, Nam Dương, Q. Hải Châu, Đà Nẵng",
    "email": "tiembanhvani.com@gmail.com"
  },
  "categories": [
    "Set bánh su",
    "Bánh tầng",
    "Bánh kẹo, chocolate",
    "Bánh mới",
    "Bánh mini",
    "Bánh mừng thọ ông bà",
    "Bánh ngọt mỗi ngày",
    "Mousse dừa",
    "Mix Vị",
    "Red velvet",
    "Bánh hũ vàng & khai trương",
    "Bánh nặn tạo hình",
    "Bánh mẫu tim",
    "Bánh 18+",
    "Bánh chủ đề theo yêu cầu",
    "Bánh chữ & số",
    "Bánh cưới",
    "Bánh hoa",
    "Bánh trái cây",
    "Bánh búp bê",
    "Bánh máy bay, ô tô, siêu nhân",
    "Bánh kem con vật",
    "Bánh logo & công ty",
    "Bánh vẽ",
    "Bánh bé gái",
    "Bánh bé trai",
    "Cupcake",
    "Bông lan trứng muối",
    "Mousse/Cheese Cake"
  ],
  "policies": {
    "order_lead_time": "",
    "delivery": "",
    "deposit": ""
  },
  "_sources": [
    {
      "url": "https://tiembanhvani.com/collections/all",
      "json": {
        "products": [
          {
            "name": "bánh kem baby three",
            "description": "",
            "category": "",
            "price_range": "0₫"
          },
          {
            "name": "mousse dừa size 18x36",
            "description": "",
            "category": "",
            "price_range": "0₫"
          },
          {
            "name": "cupcake",
            "description": "",
            "category": "",
            "price_range": "0₫"
          },
          {
            "name": "bánh kem cưới",
            "description": "",
            "category": "",
            "price_range": "0₫"
          },
          {
            "name": "bánh kem pokemon",
            "description": "",
            "category": "",
            "price_range": "0₫"
          },
          {
            "name": "bánh kem 2 tầng - nam",
            "description": "",
            "category": "",
            "price_range": "0₫"
          },
          {
            "name": "bánh kem 2 tầng - bé gái",
            "description": "",
            "category": "",
            "price_range": "0₫"
          },
          {
            "name": "bánh kem 2 tầng - công ty",
            "description": "",
            "category": "",
            "price_range": "0₫"
          },
          {
            "name": "bánh kem số",
            "description": "",
            "category": "",
            "price_range": "0₫"
          },
          {
            "name": "bánh kem công ty",
            "description": "",
            "category": "",
            "price_range": "0₫"
          },
          {
            "name": "bánh kem tim",
            "description": "",
            "category": "",
            "price_range": "0₫"
          },
          {
            "name": "bánh kem quả mông",
            "description": "",
            "category": "",
            "price_range": "0₫"
          },
          {
            "name": "bánh kem xe cảnh sát",
            "description": "",
            "category": "",
            "price_range": "0₫"
          },
          {
            "name": "bánh kemcon vật",
            "description": "",
            "category": "",
            "price_range": "0₫"
          },
          {
            "name": "bánh kem con mèo",
            "description": "",
            "category": "",
            "price_range": "0₫"
          },
          {
            "name": "bánh kem con mèo thần tài",
            "description": "",
            "category": "",
            "price_range": "0₫"
          },
          {
            "name": "bánh kem capybara",
            "description": "",
            "category": "",
            "price_range": "0₫"
          }
        ],
        "contact": {
          "phone": "0935226206",
          "address": "",
          "email": "",
          "zalo": "https://zalo.me/0935226206"
        },
        "categories": [
          "Set bánh su",
          "Bánh tầng",
          "Bánh kẹo, chocolate",
          "Bánh mới",
          "Bánh mini",
          "Bánh mừng thọ ông bà",
          "Bánh ngọt mỗi ngày",
          "Mousse dừa",
          "Mix Vị",
          "Red velvet",
          "Bánh hũ vàng & khai trương",
          "Bánh nặn tạo hình",
          "Bánh mẫu tim",
          "Bánh 18+",
          "Bánh chủ đề theo yêu cầu",
          "Bánh chữ & số",
          "Bánh cưới",
          "Bánh hoa",
          "Bánh trái cây",
          "Bánh búp bê",
          "Bánh máy bay, ô tô, siêu nhân",
          "Bánh kem con vật",
          "Bánh logo & công ty",
          "Bánh vẽ",
          "Bánh bé gái",
          "Bánh bé trai",
          "Cupcake",
          "Bông lan trứng muối"
        ],
        "policies": {
          "order_lead_time": "",
          "delivery": "",
          "deposit": ""
        }
      }
    },
    {
      "url": "https://tiembanhvani.com/pages/banh-kem",
      "json": {
        "products": [
          {
            "name": "Bánh tầng",
            "description": "Bánh tầng với nhiều sản phẩm.",
            "category": "Bánh tầng",
            "price_range": "null"
          },
          {
            "name": "Bánh kẹo, chocolate",
            "description": "Bánh kẹo và chocolate với nhiều sản phẩm.",
            "category": "Bánh kẹo, chocolate",
            "price_range": "null"
          },
          {
            "name": "Bánh mới",
            "description": "Các loại bánh mới nhất.",
            "category": "Bánh mới",
            "price_range": "null"
          },
          {
            "name": "Bánh mini",
            "description": "Bánh mini cho những dịp đặc biệt.",
            "category": "Bánh mini",
            "price_range": "null"
          },
          {
            "name": "Bánh mừng thọ ông bà",
            "description": "Bánh dành cho dịp mừng thọ ông bà.",
            "category": "Bánh mừng thọ ông bà",
            "price_range": "null"
          },
          {
            "name": "Bánh ngọt mỗi ngày",
            "description": "Bánh ngọt cho mỗi ngày.",
            "category": "Bánh ngọt mỗi ngày",
            "price_range": "null"
          },
          {
            "name": "Bánh hũ vàng & khai trương",
            "description": "Bánh để chúc mừng khai trương.",
            "category": "Bánh hũ vàng & khai trương",
            "price_range": "null"
          },
          {
            "name": "Bánh nặn tạo hình",
            "description": "Bánh được tạo hình theo yêu cầu.",
            "category": "Bánh nặn tạo hình",
            "price_range": "null"
          },
          {
            "name": "Bánh mẫu tim",
            "description": "Bánh hình mẫu tim.",
            "category": "Bánh mẫu tim",
            "price_range": "null"
          },
          {
            "name": "Bánh 18+",
            "description": "Bánh cho độ tuổi 18.",
            "category": "Bánh 18+",
            "price_range": "null"
          },
          {
            "name": "Bánh chủ đề theo yêu cầu",
            "description": "Bánh theo chủ đề yêu cầu của khách hàng.",
            "category": "Bánh chủ đề theo yêu cầu",
            "price_range": "null"
          },
          {
            "name": "Bánh chữ & số",
            "description": "Bánh với chữ và số.",
            "category": "Bánh chữ & số",
            "price_range": "null"
          },
          {
            "name": "Bánh cưới",
            "description": "Bánh cưới cho ngày trọng đại.",
            "category": "Bánh cưới",
            "price_range": "null"
          },
          {
            "name": "Bánh hoa",
            "description": "Bánh trang trí hoa.",
            "category": "Bánh hoa",
            "price_range": "null"
          },
          {
            "name": "Bánh trái cây",
            "description": "Bánh với trái cây tươi.",
            "category": "Bánh trái cây",
            "price_range": "null"
          },
          {
            "name": "Bánh búp bê",
            "description": "Bánh hình búp bê.",
            "category": "Bánh búp bê",
            "price_range": "null"
          },
          {
            "name": "Bánh máy bay, ô tô, siêu nhân",
            "description": "Bánh với hình máy bay, ô tô, siêu nhân.",
            "category": "Bánh máy bay, ô tô, siêu nhân",
            "price_range": "null"
          },
          {
            "name": "Bánh kem con vật",
            "description": "Bánh kem hình con vật.",
            "category": "Bánh kem con vật",
            "price_range": "null"
          },
          {
            "name": "Bánh logo & công ty",
            "description": "Bánh với logo công ty.",
            "category": "Bánh logo & công ty",
            "price_range": "null"
          },
          {
            "name": "Bánh vẽ",
            "description": "Bánh có vẽ trang trí.",
            "category": "Bánh vẽ",
            "price_range": "null"
          },
          {
            "name": "Bánh bé gái",
            "description": "Bánh dành cho bé gái.",
            "category": "Bánh bé gái",
            "price_range": "null"
          },
          {
            "name": "Bánh bé trai",
            "description": "Bánh dành cho bé trai.",
            "category": "Bánh bé trai",
            "price_range": "null"
          }
        ],
        "contact": {
          "phone": "0935226206",
          "address": "null",
          "email": "null",
          "zalo": "https://zalo.me/0935226206"
        },
        "categories": [
          "Bánh tầng",
          "Bánh kẹo, chocolate",
          "Bánh mới",
          "Bánh mini",
          "Bánh mừng thọ ông bà",
          "Bánh ngọt mỗi ngày",
          "Bánh hũ vàng & khai trương",
          "Bánh nặn tạo hình",
          "Bánh mẫu tim",
          "Bánh 18+",
          "Bánh chủ đề theo yêu cầu",
          "Bánh chữ & số",
          "Bánh cưới",
          "Bánh hoa",
          "Bánh trái cây",
          "Bánh búp bê",
          "Bánh máy bay, ô tô, siêu nhân",
          "Bánh kem con vật",
          "Bánh logo & công ty",
          "Bánh vẽ",
          "Bánh bé gái",
          "Bánh bé trai"
        ],
        "policies": {
          "order_lead_time": "null",
          "delivery": "null",
          "deposit": "null"
        }
      }
    },
    {
      "url": "https://tiembanhvani.com/pages/mousse-cheese-cake",
      "json": {
        "products": [
          {
            "name": "Mousse dừa",
            "description": "",
            "category": "Mousse/Cheese Cake",
            "price_range": ""
          },
          {
            "name": "Mix Vị",
            "description": "",
            "category": "Mousse/Cheese Cake",
            "price_range": ""
          },
          {
            "name": "Red velvet",
            "description": "",
            "category": "Mousse/Cheese Cake",
            "price_range": ""
          }
        ],
        "contact": {
          "phone": "0935226206",
          "address": "",
          "email": "",
          "zalo": "https://zalo.me/0935226206"
        },
        "categories": [
          "Mousse/Cheese Cake"
        ],
        "policies": {
          "order_lead_time": "",
          "delivery": "",
          "deposit": ""
        }
      }
    },
    {
      "url": "https://tiembanhvani.com/collections/banh-ngot-moi-ngay",
      "json": {
        "products": [
          {
            "name": "Panna cotta",
            "description": "",
            "category": "",
            "price_range": "0₫"
          },
          {
            "name": "Bánh mì chà bông sốt bơ",
            "description": "Hết hàng",
            "category": "",
            "price_range": "45,000₫"
          },
          {
            "name": "Cupcake trứng muối",
            "description": "Hết hàng",
            "category": "",
            "price_range": "60,000₫"
          },
          {
            "name": "Tart dừa nướng",
            "description": "Hết hàng",
            "category": "",
            "price_range": "15,000₫"
          },
          {
            "name": "Set mochi 4 vị",
            "description": "",
            "category": "",
            "price_range": "120,000₫"
          },
          {
            "name": "Sữa chua nếp cẩm",
            "description": "Hết hàng",
            "category": "",
            "price_range": "12,000₫"
          },
          {
            "name": "Su sầu riêng phomai",
            "description": "Hết hàng",
            "category": "",
            "price_range": "70,000₫"
          },
          {
            "name": "Bánh mì kem chocolate",
            "description": "Hết hàng",
            "category": "",
            "price_range": "50,000₫"
          },
          {
            "name": "Sữa chua trân châu đường đen",
            "description": "Hết hàng",
            "category": "",
            "price_range": "12,000₫"
          },
          {
            "name": "Chocolate Mochi cookies",
            "description": "Hết hàng",
            "category": "",
            "price_range": "20,000₫"
          },
          {
            "name": "Bánh bao chỉ",
            "description": "",
            "category": "",
            "price_range": "20,000₫"
          },
          {
            "name": "Set 3 donut nhân mix vị",
            "description": "",
            "category": "",
            "price_range": "55,000₫"
          },
          {
            "name": "Sừng trâu kimsa",
            "description": "Hết hàng",
            "category": "",
            "price_range": "70,000₫"
          },
          {
            "name": "Bánh mì kimsa",
            "description": "Hết hàng",
            "category": "",
            "price_range": "60,000₫"
          },
          {
            "name": "Sữa chua mít",
            "description": "",
            "category": "",
            "price_range": "12,000₫"
          },
          {
            "name": "Sữa chua cốm",
            "description": "",
            "category": "",
            "price_range": "12,000₫"
          },
          {
            "name": "Bánh sữa chua phomai nướng",
            "description": "",
            "category": "",
            "price_range": "40,000₫"
          },
          {
            "name": "Bánh mousse dừa hộp",
            "description": "",
            "category": "",
            "price_range": "50,000₫"
          },
          {
            "name": "Bánh phomai cháy",
            "description": "",
            "category": "",
            "price_range": "30,000₫"
          },
          {
            "name": "Bánh tiramisu ly",
            "description": "",
            "category": "",
            "price_range": "35,000₫"
          }
        ],
        "contact": {
          "phone": "0935226206",
          "address": "",
          "email": "",
          "zalo": "https://zalo.me/0935226206"
        },
        "categories": [
          "Set bánh su",
          "Bánh tầng",
          "Bánh kẹo, chocolate",
          "Bánh mới",
          "Bánh mini",
          "Bánh mừng thọ ông bà",
          "Bánh ngọt mỗi ngày",
          "Mousse dừa",
          "Mix Vị",
          "Red velvet",
          "Bánh hũ vàng & khai trương",
          "Bánh nặn tạo hình",
          "Bánh mẫu tim",
          "Bánh 18+",
          "Bánh chủ đề theo yêu cầu",
          "Bánh chữ & số",
          "Bánh cưới",
          "Bánh hoa",
          "Bánh trái cây",
          "Bánh búp bê",
          "Bánh máy bay, ô tô, siêu nhân",
          "Bánh kem con vật",
          "Bánh logo & công ty",
          "Bánh vẽ",
          "Bánh bé gái",
          "Bánh bé trai",
          "Cupcake",
          "Bông lan trứng muối"
        ],
        "policies": {
          "order_lead_time": "",
          "delivery": "",
          "deposit": ""
        }
      }
    },
    {
      "url": "https://tiembanhvani.com/pages/about-us",
      "json": {
        "products": [],
        "contact": {
          "phone": "0935226206",
          "address": "",
          "email": "",
          "zalo": "https://zalo.me/0935226206"
        },
        "categories": [],
        "policies": {
          "order_lead_time": "",
          "delivery": "",
          "deposit": ""
        }
      }
    },
    {
      "url": "https://tiembanhvani.com/pages/lien-he",
      "json": {
        "products": [],
        "contact": {
          "phone": "0935 226 206",
          "address": "107 Đ. Lê Đình Dương, Nam Dương, Q. Hải Châu, Đà Nẵng",
          "email": "tiembanhvani.com@gmail.com",
          "zalo": "0935226206"
        },
        "categories": [],
        "policies": {
          "order_lead_time": "",
          "delivery": "",
          "deposit": ""
        }
      }
    }
  ]
}